seedwork/__init__.py
seedwork/application/__init__.py
seedwork/application/command.py
seedwork/application/model.py
seedwork/domain/__init__.py
seedwork/domain/aggregate_root.py
seedwork/domain/entity.py
seedwork/domain/enumeration.py
seedwork/domain/event.py
seedwork/domain/repository/__init__.py
seedwork/domain/repository/generic.py
seedwork/domain/repository/repository.py
seedwork/domain/unit_of_work.py
seedwork/domain/value_object.py
seedwork/infrastructure/__init__.py
seedwork/infrastructure/cache/__init__.py
seedwork/infrastructure/cache/cache.py
seedwork/infrastructure/cache/r.py
seedwork/infrastructure/cache/redis.py
seedwork/infrastructure/logging/__init__.py
seedwork/infrastructure/logging/logger.py
seedwork/infrastructure/persistence/__init__.py
seedwork/infrastructure/persistence/sqlalchemy/__init__.py
seedwork/infrastructure/persistence/sqlalchemy/generic.py
seedwork/infrastructure/persistence/sqlalchemy/repository.py
seedwork/infrastructure/persistence/sqlalchemy/unit_of_work.py
seedwork/py.typed
seedwork/typings.py
seedwork_python-0.4.0.dist-info/LICENSE
seedwork_python-0.4.0.dist-info/METADATA
seedwork_python-0.4.0.dist-info/WHEEL
seedwork_python-0.4.0.dist-info/RECORD
